LICENSE.txt
MANIFEST.in
README.md
setup.cfg
setup.py
willowDb/__init__.py
willowDb/main.py
willowDb.egg-info/PKG-INFO
willowDb.egg-info/SOURCES.txt
willowDb.egg-info/dependency_links.txt
willowDb.egg-info/top_level.txt
willowDb/coreFunctions/files.py
willowDb/coreFunctions/filter.py
willowDb/coreFunctions/table.py
willowDb/coreFunctions/__pycache__/files.cpython-311.pyc
willowDb/coreFunctions/__pycache__/filter.cpython-311.pyc
willowDb/coreFunctions/__pycache__/table.cpython-311.pyc
willowDb/dbFunctions/createIndex.py
willowDb/dbFunctions/delete.py
willowDb/dbFunctions/deleteIndex.py
willowDb/dbFunctions/insert.py
willowDb/dbFunctions/query.py
willowDb/dbFunctions/scan.py
willowDb/dbFunctions/update.py
willowDb/dbFunctions/__pycache__/createIndex.cpython-311.pyc
willowDb/dbFunctions/__pycache__/delete.cpython-311.pyc
willowDb/dbFunctions/__pycache__/deleteIndex.cpython-311.pyc
willowDb/dbFunctions/__pycache__/insert.cpython-311.pyc
willowDb/dbFunctions/__pycache__/query.cpython-311.pyc
willowDb/dbFunctions/__pycache__/scan.cpython-311.pyc
willowDb/dbFunctions/__pycache__/update.cpython-311.pyc
willowDb/tables/.DS_Store
willowDb/utils/common.py
willowDb/utils/errorHandler.py
willowDb/utils/errors.py
willowDb/utils/logger.py
willowDb/utils/__pycache__/common.cpython-311.pyc
willowDb/utils/__pycache__/errorHandler.cpython-311.pyc
willowDb/utils/__pycache__/errors.cpython-311.pyc
willowDb/utils/__pycache__/logger.cpython-311.pyc